{
	"animations": [
		{
			"loop": false,
			"offsets": [
				524,
				512
			],
			"anim": "singUP",
			"fps": 24,
			"name": "Up",
			"indices": []
		},
		{
			"loop": false,
			"offsets": [
				1012,
				358
			],
			"anim": "singLEFT",
			"fps": 24,
			"name": "Left",
			"indices": []
		},
		{
			"loop": false,
			"offsets": [
				590,
				270
			],
			"anim": "idle",
			"fps": 24,
			"name": "Idle",
			"indices": []
		},
		{
			"loop": false,
			"offsets": [
				234,
				272
			],
			"anim": "singRIGHT",
			"fps": 24,
			"name": "Right",
			"indices": []
		},
		{
			"loop": false,
			"offsets": [
				470,
				30
			],
			"anim": "singDOWN",
			"fps": 24,
			"name": "Down",
			"indices": []
		}
	],
	"no_antialiasing": false,
	"image": "characters/tsukareta",
	"position": [
		0,
		0
	],
	"healthicon": "tsukareta",
	"flip_x": false,
	"healthbar_colors": [
		255,
		255,
		255
	],
	"camera_position": [
		-520,
		-120
	],
	"sing_duration": 4,
	"scale": 0.6
}